bluepost/__init__.py
bluepost/__main__.py
bluepost/__version__.py
bluepost/cli.py
bluepost/core.py
bluepost-1.2.dist-info/entry_points.txt
bluepost-1.2.dist-info/licenses/LICENSE
bluepost-1.2.dist-info/WHEEL
bluepost-1.2.dist-info/METADATA
bluepost-1.2.dist-info/RECORD
