Metadata-Version: 2.4
Name: bluepost
Version: 1.2
Summary: bluesky bot: repost everything another account posts/reposts
Author-email: Amethyst Reese <amethyst@n7.gg>
Requires-Python: >=3.12
License-Expression: MIT
License-File: LICENSE
Requires-Dist: atproto >= 0.0.60, < 1.0
Requires-Dist: click >= 8
Requires-Dist: platformdirs >= 4
Requires-Dist: pyserde >= 0.23
Requires-Dist: attribution>=1.8 ; extra == "dev"
Requires-Dist: black==25.1.0 ; extra == "dev"
Requires-Dist: build>=1.2 ; extra == "dev"
Requires-Dist: flake8==7.2.0 ; extra == "dev"
Requires-Dist: mypy==1.15.0 ; extra == "dev"
Requires-Dist: ufmt==2.8.0 ; extra == "dev"
Requires-Dist: usort==1.0.8 ; extra == "dev"
Project-URL: Home, https://github.com/amyreese/bluepost
Provides-Extra: dev
